ox_db/__init__.py
ox_db/ai/__init__.py
ox_db/ai/vector.py
ox_db/api/__init__.py
ox_db/api/log.py
ox_db/db/__init__.py
ox_db/db/log.py
ox_db/oxd/__init__.py
ox_db-0.0.71.dist-info/LICENSE
ox_db-0.0.71.dist-info/METADATA
ox_db-0.0.71.dist-info/WHEEL
ox_db-0.0.71.dist-info/top_level.txt
ox_db-0.0.71.dist-info/RECORD
