Metadata-Version: 2.1
Name: ox-db
Version: 0.0.71
Summary: A simple database and vector database
Home-page: https://github.com/ox-ai/ox-db.git
Author: Lokeshwaran M
Author-email: lokeshwaran.m23072003@gmail.com
License: MIT
Keywords: ox-db ox-ai
License-File: LICENSE
Requires-Dist: fastapi ==0.111.0
Requires-Dist: numpy ==1.24.1
Requires-Dist: pydantic ==2.7.4
Requires-Dist: pymongo ==4.8.0
Requires-Dist: sentence-transformers ==3.0.1
Requires-Dist: setuptools ==68.1.2
